{"cameraMode":{"drawMode":0,"name":"Shaded","section":"Shading Mode"},"sceneLighting":false,"audioPlay":false,"sceneViewState":{"m_AlwaysRefresh":true,"showFog":true,"showSkybox":false,"showFlares":true,"showImageEffects":true,"showParticleSystems":true,"showVisualEffectGraphs":true,"m_FxEnabled":true},"in2DMode":false,"pivot":{"x":0.0,"y":0.38840800523757937,"z":0.0},"rotation":{"x":-0.026194583624601365,"y":0.983834445476532,"z":0.004800569731742144,"w":0.1848149448633194},"size":0.5287814736366272,"orthographic":false}